{
  "project_info": {
    "project_number": "37063570331",
    "firebase_url": "https://yumfood-6ae57-default-rtdb.asia-southeast1.firebasedatabase.app",
    "project_id": "yumfood-6ae57",
    "storage_bucket": "yumfood-6ae57.appspot.com"
  },
  "client": [
    {
      "client_info": {
        "mobilesdk_app_id": "1:37063570331:android:712aedbf11354fea59e73e",
        "android_client_info": {
          "package_name": "com.example.yumfood"
        }
      },
      "oauth_client": [
        {
          "client_id": "37063570331-u6qt7r6o0k4fb80q2vqch6udfqrnilsc.apps.googleusercontent.com",
          "client_type": 1,
          "android_info": {
            "package_name": "com.example.yumfood",
            "certificate_hash": "1adee700cd3c913ec6d84ca42c62333c7ce900f3"
          }
        },
        {
          "client_id": "37063570331-59t3n29a4mu9mdsgbei78olk5oq1qq5g.apps.googleusercontent.com",
          "client_type": 3
        }
      ],
      "api_key": [
        {
          "current_key": "AIzaSyBmjqzN9pqxelCRnyUvo0KJR1r5OQeHBsQ"
        }
      ],
      "services": {
        "appinvite_service": {
          "other_platform_oauth_client": [
            {
              "client_id": "37063570331-59t3n29a4mu9mdsgbei78olk5oq1qq5g.apps.googleusercontent.com",
              "client_type": 3
            }
          ]
        }
      }
    }
  ],
  "configuration_version": "1"
}